{
  "nr_root_ast_changes": 1,
  "faulty_ast": [
    {
      "label": "STARTUP_TEXT",
      "type": "Field",
      "children": [
        {
          "label": "java.lang.String[]",
          "type": "VARIABLE_TYPE",
          "children": []
        },
        {
          "label": "",
          "type": "Modifiers",
          "children": [
            {
              "label": "final",
              "type": "Modifier",
              "children": []
            },
            {
              "label": "public",
              "type": "Modifier",
              "children": []
            },
            {
              "label": "static",
              "type": "Modifier",
              "children": []
            }
          ]
        },
        {
          "label": "",
          "type": "NewArray",
          "return_type": "java.lang.String[]",
          "children": [
            {
              "label": "\"Shotgun sequence assembly GUI\"",
              "type": "Literal",
              "susp": [
                "susp_constChange_literal"
              ],
              "return_type": "java.lang.String",
              "index_of_exper": "expression_0",
              "children": []
            },
            {
              "label": "\"Copyright (C) 2010 Matthew Ruffalo\"",
              "type": "Literal",
              "return_type": "java.lang.String",
              "index_of_exper": "expression_1",
              "children": []
            },
            {
              "label": "\"\"",
              "type": "Literal",
              "return_type": "java.lang.String",
              "index_of_exper": "expression_2",
              "children": []
            },
            {
              "label": "\"This program is free software: you can redistribute it and/or modify\"",
              "type": "Literal",
              "return_type": "java.lang.String",
              "index_of_exper": "expression_3",
              "children": []
            },
            {
              "label": "\"it under the terms of the GNU General Public License as published by\"",
              "type": "Literal",
              "return_type": "java.lang.String",
              "index_of_exper": "expression_4",
              "children": []
            },
            {
              "label": "\"the Free Software Foundation, either version 3 of the License, or\"",
              "type": "Literal",
              "return_type": "java.lang.String",
              "index_of_exper": "expression_5",
              "children": []
            },
            {
              "label": "\"(at your option) any later version.\"",
              "type": "Literal",
              "return_type": "java.lang.String",
              "index_of_exper": "expression_6",
              "children": []
            },
            {
              "label": "\"\"",
              "type": "Literal",
              "return_type": "java.lang.String",
              "index_of_exper": "expression_2",
              "children": []
            },
            {
              "label": "\"This program is distributed in the hope that it will be useful,\"",
              "type": "Literal",
              "return_type": "java.lang.String",
              "index_of_exper": "expression_7",
              "children": []
            },
            {
              "label": "\"but WITHOUT ANY WARRANTY; without even the implied warranty of\"",
              "type": "Literal",
              "return_type": "java.lang.String",
              "index_of_exper": "expression_8",
              "children": []
            },
            {
              "label": "\"MERCHANTABILITY or FITNESS FOR A PARTICULAR PURPOSE.  See the\"",
              "type": "Literal",
              "return_type": "java.lang.String",
              "index_of_exper": "expression_9",
              "children": []
            },
            {
              "label": "\"GNU General Public License for more details.\"",
              "type": "Literal",
              "return_type": "java.lang.String",
              "index_of_exper": "expression_10",
              "children": []
            },
            {
              "label": "\"\"",
              "type": "Literal",
              "return_type": "java.lang.String",
              "index_of_exper": "expression_2",
              "children": []
            },
            {
              "label": "\"You should have received a copy of the GNU General Public License\"",
              "type": "Literal",
              "return_type": "java.lang.String",
              "index_of_exper": "expression_11",
              "children": []
            },
            {
              "label": "\"along with this program.  If not, see \u003chttp://www.gnu.org/licenses/\u003e.\"",
              "type": "Literal",
              "return_type": "java.lang.String",
              "index_of_exper": "expression_12",
              "children": []
            }
          ]
        }
      ]
    }
  ],
  "context": {
    "cntx": {
      "S1_LOCAL_VAR_NOT_ASSIGNED": "false",
      "S14_TYPE_OF_FAULTY_STATEMENT_PARENT": "Class",
      "S9_METHOD_CALL_WITH_NORMAL_GUARD": "false",
      "S2_SIMILAR_OBJECT_TYPE_WITH_NORMAL_GUARD": "false",
      "S4_Field_NOT_USED": "false",
      "S18_In_Synchronized_Method": "false",
      "S8_PRIMITIVE_USED_IN_ASSIGNMENT": "false",
      "S11_FAULTY_CLASS_EXCEPTION_TYPE": "false",
      "S16_HAS_Invocations_Prone_Exception": "false",
      "S7_OBJECT_USED_IN_ASSIGNMENT": "false",
      "S5_SIMILAR_PRIMITIVE_TYPE_WITH_NULL_GUARD": "false",
      "S13_TYPE_OF_FAULTY_STATEMENT_BEFORE_2": "",
      "S13_TYPE_OF_FAULTY_STATEMENT_BEFORE_1": "",
      "S13_TYPE_OF_FAULTY_STATEMENT_BEFORE_3": "",
      "S12_METHOD_CALL_WITH_TRY_CATCH": "false",
      "CONSTANT": {
        "\"\"": {
          "C1_SAME_TYPE_CONSTANT": "true",
          "C2_SAME_TYPE_CONSTANT_VAR": "false",
          "C2_SAME_TYPE_VAR": "false"
        },
        "\"(at your option) any later version.\"": {
          "C1_SAME_TYPE_CONSTANT": "true",
          "C2_SAME_TYPE_CONSTANT_VAR": "false",
          "C2_SAME_TYPE_VAR": "false"
        },
        "\"This program is free software: you can redistribute it and/or modify\"": {
          "C1_SAME_TYPE_CONSTANT": "true",
          "C2_SAME_TYPE_CONSTANT_VAR": "false",
          "C2_SAME_TYPE_VAR": "false"
        },
        "\"You should have received a copy of the GNU General Public License\"": {
          "C1_SAME_TYPE_CONSTANT": "true",
          "C2_SAME_TYPE_CONSTANT_VAR": "false",
          "C2_SAME_TYPE_VAR": "false"
        },
        "\"it under the terms of the GNU General Public License as published by\"": {
          "C1_SAME_TYPE_CONSTANT": "true",
          "C2_SAME_TYPE_CONSTANT_VAR": "false",
          "C2_SAME_TYPE_VAR": "false"
        },
        "\"GNU General Public License for more details.\"": {
          "C1_SAME_TYPE_CONSTANT": "true",
          "C2_SAME_TYPE_CONSTANT_VAR": "false",
          "C2_SAME_TYPE_VAR": "false"
        },
        "\"the Free Software Foundation, either version 3 of the License, or\"": {
          "C1_SAME_TYPE_CONSTANT": "true",
          "C2_SAME_TYPE_CONSTANT_VAR": "false",
          "C2_SAME_TYPE_VAR": "false"
        },
        "\"Copyright (C) 2010 Matthew Ruffalo\"": {
          "C1_SAME_TYPE_CONSTANT": "true",
          "C2_SAME_TYPE_CONSTANT_VAR": "false",
          "C2_SAME_TYPE_VAR": "false"
        },
        "\"Shotgun sequence assembly GUI\"": {
          "C1_SAME_TYPE_CONSTANT": "true",
          "C2_SAME_TYPE_CONSTANT_VAR": "false",
          "C2_SAME_TYPE_VAR": "false"
        },
        "\"MERCHANTABILITY or FITNESS FOR A PARTICULAR PURPOSE.  See the\"": {
          "C1_SAME_TYPE_CONSTANT": "true",
          "C2_SAME_TYPE_CONSTANT_VAR": "false",
          "C2_SAME_TYPE_VAR": "false"
        },
        "\"along with this program.  If not, see \u003chttp://www.gnu.org/licenses/\u003e.\"": {
          "C1_SAME_TYPE_CONSTANT": "true",
          "C2_SAME_TYPE_CONSTANT_VAR": "false",
          "C2_SAME_TYPE_VAR": "false"
        },
        "\"but WITHOUT ANY WARRANTY; without even the implied warranty of\"": {
          "C1_SAME_TYPE_CONSTANT": "true",
          "C2_SAME_TYPE_CONSTANT_VAR": "false",
          "C2_SAME_TYPE_VAR": "false"
        },
        "\"This program is distributed in the hope that it will be useful,\"": {
          "C1_SAME_TYPE_CONSTANT": "true",
          "C2_SAME_TYPE_CONSTANT_VAR": "false",
          "C2_SAME_TYPE_VAR": "false"
        }
      },
      "S10_METHOD_CALL_WITH_NULL_GUARD": "false",
      "S5_SIMILAR_PRIMITIVE_TYPE_WITH_NORMAL_GUARD": "false",
      "S2_SIMILAR_OBJECT_TYPE_WITH_NULL_GUARD": "false",
      "S4_Field_NOT_ASSIGNED": "false",
      "S13_TYPE_OF_FAULTY_STATEMENT_AFTER_1": "",
      "S1_LOCAL_VAR_NOT_USED": "false",
      "S3_TYPE_OF_FAULTY_STATEMENT": "Field",
      "S13_TYPE_OF_FAULTY_STATEMENT_AFTER_3": "",
      "S13_TYPE_OF_FAULTY_STATEMENT_AFTER_2": "",
      "S15_HAS_OBJECTIVE_METHOD_CALL": "false"
    }
  }
}